pulumi_harvester
