Metadata-Version: 2.1
Name: pulumi-harvester
Version: 0.1.1
Summary: A Pulumi package for creating and managing harvester cloud resources.
Home-page: https://www.pulumi.com
License: Apache-2.0
Project-URL: Repository, https://github.com/huaxk/pulumi-harvester
Keywords: pulumi harvester
Platform: UNKNOWN
